funapi/__init__.py
funword-0.0.1.dist-info/LICENSE
funword-0.0.1.dist-info/METADATA
funword-0.0.1.dist-info/WHEEL
funword-0.0.1.dist-info/entry_points.txt
funword-0.0.1.dist-info/top_level.txt
funword-0.0.1.dist-info/RECORD
